{
    "He4": {
        "error": 12.131495627834202,
        "error_type": "SEM",
        "filter_outliers_dict": {
            "filter_outliers": true,
            "iterations": 1,
            "std_devs": 2,
            "use_iqr_filtering": false,
            "use_standard_deviation_filtering": true
        },
        "fit": "linear",
        "fn": 300,
        "include_baseline_error": true,
        "n": 300,
        "outlier_excluded": [],
        "reviewed": true,
        "user_excluded": [],
        "value": 1558.5557265119496
    }
}