{
    "He4": {
        "error": 5.522813725913057,
        "error_type": "SEM",
        "filter_outliers_dict": {
            "filter_outliers": true,
            "iterations": 1,
            "std_devs": 2,
            "use_iqr_filtering": false,
            "use_standard_deviation_filtering": true
        },
        "fit": "linear",
        "fn": 286,
        "include_baseline_error": true,
        "n": 300,
        "outlier_excluded": [
            292,
            186,
            296,
            250,
            299,
            140,
            204,
            219,
            111,
            273,
            52,
            84,
            26,
            91
        ],
        "reviewed": true,
        "user_excluded": [],
        "value": 637.3969582271047
    }
}